aau_ais_dipaal-0.1.29.dist-info/METADATA
aau_ais_dipaal-0.1.29.dist-info/WHEEL
dipaal/__init__.py
dipaal/convert/__init__.py
dipaal/convert/callsign.py
dipaal/convert/converter.py
dipaal/convert/imo.py
dipaal/convert/mmsi.py
dipaal/export/__init__.py
dipaal/export/map_exporter.py
dipaal/export/sql/map.py
dipaal/extract/__init__.py
dipaal/extract/draught.py
dipaal/extract/grid.py
dipaal/extract/sql/__init__.py
dipaal/extract/sql/draught_mmsi.py
dipaal/extract/sql/grid_fact_depth.py
dipaal/list/__init__.py
dipaal/list/lister.py
dipaal/list/sql/enc.sql
dipaal/list/sql/ship_type.sql
dipaal/load/__init__.py
dipaal/load/loader.py
dipaal/load/sql/dipaal_to_depth/02.load.fact_depth_50m.sql
dipaal/load/sql/dipaal_to_depth/04.update.confidence.fact_depth_50m.sql
dipaal/load/sql/dipaal_to_depth/04x1.post_processeing.sql
dipaal/load/sql/dipaal_to_depth/04x2.post_processeing.sql
dipaal/load/sql/dipaal_to_depth/06.load.fact_raster_confidence.sql
dipaal/load/sql/dipaal_to_depth/08.load.fact_raster_confidence_month.sql
dipaal/settings.py
aau_ais_dipaal-0.1.29.dist-info/RECORD
